<?xml version="1.0" encoding="UTF-8"?><ab xmlns="http://www.tei-c.org/ns/1.0" type="dDay" xml:id="g1791-11-28"><date xmlns="http://www.tei-c.org/ns/1.0" when="1791-11-28">28. M. </date><ref xmlns="http://www.tei-c.org/ns/1.0" type="dWrote" subtype="transcr" target="/works/poli01.html">Transcribe 4 pages</ref>: <ref xmlns="http://www.tei-c.org/ns/1.0" type="dWrote" subtype="corr" target="/works/poli01.html">correct:<seg xmlns="http://www.tei-c.org/ns/1.0" type="dWrote" subtype="write"> write
                     1</seg></ref>. <ref xmlns="http://www.tei-c.org/ns/1.0" type="dText" subtype="read" target="/bibl/te0045.html">Pucelle</ref>. <seg xmlns="http://www.tei-c.org/ns/1.0" type="dMeal" subtype="SG"><persName xmlns="http://www.tei-c.org/ns/1.0">John</persName> sups</seg>. <ref xmlns="http://www.tei-c.org/ns/1.0" type="dText" subtype="read" target="/bibl/te0055.html">Dict.
                  Phil</ref>.</ab>