<?xml version="1.0" encoding="UTF-8"?><ab xmlns="http://www.tei-c.org/ns/1.0" type="dDay" xml:id="g1791-11-04"><date xmlns="http://www.tei-c.org/ns/1.0" when="1791-11-04">4. F. </date><seg xmlns="http://www.tei-c.org/ns/1.0" type="dMeeting" subtype="C">Call on <persName xmlns="http://www.tei-c.org/ns/1.0" ref="/people/HOL02.html"><placeName xmlns="http://www.tei-c.org/ns/1.0" type="venue">B. Hollis</placeName></persName></seg>, <seg xmlns="http://www.tei-c.org/ns/1.0" type="dMeeting" subtype="C"><persName xmlns="http://www.tei-c.org/ns/1.0"><placeName xmlns="http://www.tei-c.org/ns/1.0" type="venue">Henley</placeName></persName></seg>, <persName xmlns="http://www.tei-c.org/ns/1.0" ref="/people/ROB01.html">Robinson</persName> &amp; <seg xmlns="http://www.tei-c.org/ns/1.0" type="dMeeting" subtype="C"><persName xmlns="http://www.tei-c.org/ns/1.0" ref="/people/WEB01.html"><placeName xmlns="http://www.tei-c.org/ns/1.0" type="venue">M<hi xmlns="http://www.tei-c.org/ns/1.0" rend="sup">rs</hi> Webb</placeName></persName></seg>. <ref xmlns="http://www.tei-c.org/ns/1.0" type="dEvent" subtype="Publ" target="/events/pu0051.html"><seg xmlns="http://www.tei-c.org/ns/1.0" type="dMeal" subtype="D">Dine at the <placeName xmlns="http://www.tei-c.org/ns/1.0">London Tavern</placeName>, With <persName xmlns="http://www.tei-c.org/ns/1.0" ref="/people/PAI01.html">Paine</persName>, <persName xmlns="http://www.tei-c.org/ns/1.0" ref="/people/PET01.html">Pethion</persName>,
                        <persName xmlns="http://www.tei-c.org/ns/1.0" ref="/people/TOO01.html">Horne Tooke</persName>, <persName xmlns="http://www.tei-c.org/ns/1.0" ref="/people/PRI01.html">Priestley</persName>, <persName xmlns="http://www.tei-c.org/ns/1.0" ref="/people/KIP01.html">Kippis</persName>, <persName xmlns="http://www.tei-c.org/ns/1.0" ref="/people/REE02.html">Rees</persName>, <persName xmlns="http://www.tei-c.org/ns/1.0" ref="/people/HOL02.html">B. Hollis</persName>,
                        <persName xmlns="http://www.tei-c.org/ns/1.0" ref="/people/LIS01.html">Listers</persName>, <persName xmlns="http://www.tei-c.org/ns/1.0" ref="/people/MOR03|MOR04.html">Morgans</persName></seg></ref>. <ref xmlns="http://www.tei-c.org/ns/1.0" type="dEvent" subtype="Trial" target="/events/tr0002.html"><placeName xmlns="http://www.tei-c.org/ns/1.0">Birmingham</placeName> Trials</ref>.</ab>