<?xml version="1.0" encoding="UTF-8"?><ab xmlns="http://www.tei-c.org/ns/1.0" type="dDay" xml:id="g1792-04-29"><date xmlns="http://www.tei-c.org/ns/1.0" when="1792-04-29">Apr. 29. Su.</date><seg xmlns="http://www.tei-c.org/ns/1.0" type="dMeeting" subtype="C">Call on <persName xmlns="http://www.tei-c.org/ns/1.0" ref="/people/FEN01.html">Fenwick</persName>, with <persName xmlns="http://www.tei-c.org/ns/1.0" ref="/people/DYS01.html">Dyson</persName>, talk to the latter of <seg xmlns="http://www.tei-c.org/ns/1.0" type="dTopic">Greek</seg></seg>. <seg xmlns="http://www.tei-c.org/ns/1.0" type="dMeal" subtype="D">Dine with <persName xmlns="http://www.tei-c.org/ns/1.0"><placeName xmlns="http://www.tei-c.org/ns/1.0" type="venue">Dorothy</placeName></persName></seg>. <seg xmlns="http://www.tei-c.org/ns/1.0" type="dMeal" subtype="S">Sup at <persName xmlns="http://www.tei-c.org/ns/1.0" ref="/people/NIC01.html"><placeName xmlns="http://www.tei-c.org/ns/1.0" type="venue">Nicholson</placeName></persName>, <ref xmlns="http://www.tei-c.org/ns/1.0" type="dWrote" subtype="revised" target="/works/poli01.html"><foreign xmlns="http://www.tei-c.org/ns/1.0">revisal de mon ouvrage</foreign></ref></seg>. <seg xmlns="http://www.tei-c.org/ns/1.0" type="dMeeting" subtype="CG"><persName xmlns="http://www.tei-c.org/ns/1.0" ref="/people/HOL02.html" type="nah">B. Hollis</persName> calls, nah</seg>.</ab>