<?xml version="1.0" encoding="UTF-8"?><ab xmlns="http://www.tei-c.org/ns/1.0" type="dDay" xml:id="g1794-03-06"><date xmlns="http://www.tei-c.org/ns/1.0" when="1794-03-06">6. Th.</date><ref xmlns="http://www.tei-c.org/ns/1.0" type="dText" subtype="read" target="/bibl/te0465.html">Shaftesbury, p. 143</ref>: <ref xmlns="http://www.tei-c.org/ns/1.0" type="dText" subtype="read" target="/bibl/te0470.html">Mallet du Pan, pp. 112</ref>: <ref xmlns="http://www.tei-c.org/ns/1.0" type="dText" subtype="read" target="/bibl/te0317.html">Hooke, p. 140</ref>. <seg xmlns="http://www.tei-c.org/ns/1.0" type="dMeeting" subtype="C">Call on <persName xmlns="http://www.tei-c.org/ns/1.0" ref="/people/REV02.html"><placeName xmlns="http://www.tei-c.org/ns/1.0" type="venue">Reveley</placeName></persName></seg> &amp; <seg xmlns="http://www.tei-c.org/ns/1.0" type="dMeeting" subtype="C"><persName xmlns="http://www.tei-c.org/ns/1.0" ref="/people/JEN01.html" type="nah"><placeName xmlns="http://www.tei-c.org/ns/1.0" type="venue">Jennings</placeName></persName>, nah</seg>.</ab>