<?xml version="1.0" encoding="UTF-8"?><ab xmlns="http://www.tei-c.org/ns/1.0" type="dDay" xml:id="g1798-08-17"><date xmlns="http://www.tei-c.org/ns/1.0" when="1798-08-17">17. F.</date><ref xmlns="http://www.tei-c.org/ns/1.0" type="dWrote" subtype="write" target="/works/leon01.html">St Leon, p. 66</ref>. <ref xmlns="http://www.tei-c.org/ns/1.0" type="dText" subtype="read" target="/bibl/te0859.html">Ovid, p. 57</ref>: <ref xmlns="http://www.tei-c.org/ns/1.0" type="dText" subtype="read" target="/bibl/te0833.html">Julie,
                  p. 340, fin</ref>. <seg xmlns="http://www.tei-c.org/ns/1.0" type="dMeeting" subtype="C">Call on <persName xmlns="http://www.tei-c.org/ns/1.0" ref="/people/KEI01.html" type="nah"><placeName xmlns="http://www.tei-c.org/ns/1.0" type="venue">Keir</placeName></persName><hi xmlns="http://www.tei-c.org/ns/1.0" rend="sup">n</hi></seg>: <seg xmlns="http://www.tei-c.org/ns/1.0" type="dMeal" subtype="SG"><persName xmlns="http://www.tei-c.org/ns/1.0" ref="/people/GOD04.html">H G</persName> sups</seg>: <seg xmlns="http://www.tei-c.org/ns/1.0" type="dMeal" subtype="DG"><persName xmlns="http://www.tei-c.org/ns/1.0" ref="/people/MAR01.html">M</persName> dines</seg>: <seg xmlns="http://www.tei-c.org/ns/1.0" type="dMeeting" subtype="CG"><persName xmlns="http://www.tei-c.org/ns/1.0" ref="/people/RIT01.html">Ritson</persName> calls</seg>.</ab>