<?xml version="1.0" encoding="UTF-8"?><ab xmlns="http://www.tei-c.org/ns/1.0" type="dDay" xml:id="g1798-01-13"><date xmlns="http://www.tei-c.org/ns/1.0" when="1798-01-13">13. Sa.</date><ref xmlns="http://www.tei-c.org/ns/1.0" type="dText" subtype="read" target="/bibl/te0040.html">Appeal, p. 70</ref>: <ref xmlns="http://www.tei-c.org/ns/1.0" type="dText" subtype="read" target="/bibl/te0812.html">Reynolds, p. 14</ref>. <seg xmlns="http://www.tei-c.org/ns/1.0" type="dMeal" subtype="D">Dine at <persName xmlns="http://www.tei-c.org/ns/1.0" ref="/people/HOL02.html"><placeName xmlns="http://www.tei-c.org/ns/1.0" type="venue">B Hollis's</placeName></persName>, w. <persName xmlns="http://www.tei-c.org/ns/1.0" ref="/people/NIC03.html">Nichols</persName>,
                  <persName xmlns="http://www.tei-c.org/ns/1.0">Batleys</persName>, <persName xmlns="http://www.tei-c.org/ns/1.0" ref="/people/GED01.html">Geddes</persName>, <persName xmlns="http://www.tei-c.org/ns/1.0" ref="/people/DIS01.html">Disney</persName>, <persName xmlns="http://www.tei-c.org/ns/1.0" ref="/people/WHI03.html">White</persName>,
                     <persName xmlns="http://www.tei-c.org/ns/1.0">Jervis</persName> &amp; <persName xmlns="http://www.tei-c.org/ns/1.0" ref="/people/TOW03.html">Towers
                  jun</persName></seg>.</ab>