<?xml version="1.0" encoding="UTF-8"?><ab xmlns="http://www.tei-c.org/ns/1.0" type="dDay" xml:id="g1800-09-01"><date xmlns="http://www.tei-c.org/ns/1.0" when="1800-09-01">Sep. 1. M.</date><ref xmlns="http://www.tei-c.org/ns/1.0" type="dText" subtype="read" target="/bibl/te1115.html">Etymologicum Magnum</ref>. <seg xmlns="http://www.tei-c.org/ns/1.0" type="dMeal" subtype="D">Dine
                  at <persName xmlns="http://www.tei-c.org/ns/1.0" ref="/people/ROB04.html"><placeName xmlns="http://www.tei-c.org/ns/1.0" type="venue">mrs Robinson's</placeName></persName> (<placeName xmlns="http://www.tei-c.org/ns/1.0">Englefield Green</placeName>), w. <persName xmlns="http://www.tei-c.org/ns/1.0" ref="/people/MAR01.html">M</persName></seg>: <seg xmlns="http://www.tei-c.org/ns/1.0" type="dMeeting" subtype="M">m<hi xmlns="http://www.tei-c.org/ns/1.0" rend="sup">t</hi><persName xmlns="http://www.tei-c.org/ns/1.0" ref="/people/GAW01.html">Gawler</persName></seg>: <ref xmlns="http://www.tei-c.org/ns/1.0" type="dEvent" subtype="PersHlth" target="/events/he0000.html">sleep</ref>.</ab>