<?xml version="1.0" encoding="UTF-8"?><ab xmlns="http://www.tei-c.org/ns/1.0" type="dDay" xml:id="g1802-08-09"><date xmlns="http://www.tei-c.org/ns/1.0" when="1802-08-09">9. M.</date><ref xmlns="http://www.tei-c.org/ns/1.0" type="dText" subtype="cala" target="/bibl/te1328.html">Percy, çala</ref>. <seg xmlns="http://www.tei-c.org/ns/1.0" type="dMeeting" subtype="C">Call on <persName xmlns="http://www.tei-c.org/ns/1.0" ref="/people/BEC01.html" type="nah"><placeName xmlns="http://www.tei-c.org/ns/1.0" type="venue">J Beccaria</placeName></persName><hi xmlns="http://www.tei-c.org/ns/1.0" rend="sup">n</hi></seg>: <ref xmlns="http://www.tei-c.org/ns/1.0" type="dEntertainment" subtype="Theat" target="/plays/unkn24.html"><placeName xmlns="http://www.tei-c.org/ns/1.0" type="AC"/><placeName xmlns="http://www.tei-c.org/ns/1.0">Astley's</placeName>, 1/2 Female Hussar</ref>. <seg xmlns="http://www.tei-c.org/ns/1.0" type="dMeeting" subtype="CG"><persName xmlns="http://www.tei-c.org/ns/1.0">Ingersol</persName> calls</seg>, &amp; <seg xmlns="http://www.tei-c.org/ns/1.0" type="dMeeting" subtype="CG"><persName xmlns="http://www.tei-c.org/ns/1.0">messenger</persName> from <persName xmlns="http://www.tei-c.org/ns/1.0">Warburton, schoolmaster</persName></seg>.</ab>