<?xml version="1.0" encoding="UTF-8"?><ab xmlns="http://www.tei-c.org/ns/1.0" type="dDay" xml:id="g1804-09-11"><date xmlns="http://www.tei-c.org/ns/1.0" when="1804-09-11">11. Tu.</date><ref xmlns="http://www.tei-c.org/ns/1.0" type="dText" subtype="cala" target="/bibl/te1455.html">Cowley, çala</ref>. <seg xmlns="http://www.tei-c.org/ns/1.0" type="dMeeting" subtype="C">Call on <persName xmlns="http://www.tei-c.org/ns/1.0" ref="/people/JOH01.html"><placeName xmlns="http://www.tei-c.org/ns/1.0" type="venue">Johnson</placeName></persName></seg> &amp; <seg xmlns="http://www.tei-c.org/ns/1.0" type="dMeeting" subtype="C"><persName xmlns="http://www.tei-c.org/ns/1.0" ref="/people/LAM01.html"><placeName xmlns="http://www.tei-c.org/ns/1.0" type="venue">Lamb</placeName></persName>; <seg xmlns="http://www.tei-c.org/ns/1.0" type="dMeeting" subtype="Adv">adv. <persName xmlns="http://www.tei-c.org/ns/1.0" ref="/people/COO01.html">Cooper</persName></seg></seg>: <seg xmlns="http://www.tei-c.org/ns/1.0" type="dMeal" subtype="DG"><persName xmlns="http://www.tei-c.org/ns/1.0" ref="/people/COO01.html">Cooper</persName>, <persName xmlns="http://www.tei-c.org/ns/1.0" ref="/people/WOL03.html">Wts</persName>,
                     <persName xmlns="http://www.tei-c.org/ns/1.0" ref="/people/HOL06.html">F Ht</persName> &amp; <persName xmlns="http://www.tei-c.org/ns/1.0" ref="/people/GOD01.html">J
                  G</persName> dine</seg>.</ab>