<?xml version="1.0" encoding="UTF-8"?><ab xmlns="http://www.tei-c.org/ns/1.0" type="dDay" xml:id="g1805-09-02"><date xmlns="http://www.tei-c.org/ns/1.0" when="1805-09-02">2. M. </date><ref xmlns="http://www.tei-c.org/ns/1.0" type="dText" subtype="read" target="/bibl/te1579.html">Chapman, B. XI</ref>: <ref xmlns="http://www.tei-c.org/ns/1.0" type="dText" subtype="read" target="/bibl/te1583.html">Drayton, Numphidia</ref>. <seg xmlns="http://www.tei-c.org/ns/1.0" type="dMeeting" subtype="C">Call on <persName xmlns="http://www.tei-c.org/ns/1.0"><placeName xmlns="http://www.tei-c.org/ns/1.0" type="venue">Wilks</placeName></persName></seg>: <seg xmlns="http://www.tei-c.org/ns/1.0" type="dMeeting" subtype="CG"><persName xmlns="http://www.tei-c.org/ns/1.0" ref="/people/NIC01.html" type="nah">Nicholson</persName> calls <hi xmlns="http://www.tei-c.org/ns/1.0" rend="sup">n</hi></seg>. <ref xmlns="http://www.tei-c.org/ns/1.0" type="dText" subtype="read" target="/bibl/te1584.html">Boileau, Reflexions</ref>.</ab>