<?xml version="1.0" encoding="UTF-8"?><ab xmlns="http://www.tei-c.org/ns/1.0" type="dDay" xml:id="g1807-05-29"><date xmlns="http://www.tei-c.org/ns/1.0" when="1807-05-29">29. F.</date><ref xmlns="http://www.tei-c.org/ns/1.0" type="dText" subtype="read" target="/bibl/te1656.html">Faux Dauphin, 2 Vs</ref>. <seg xmlns="http://www.tei-c.org/ns/1.0" type="dMeal" subtype="DG"><persName xmlns="http://www.tei-c.org/ns/1.0" ref="/people/ROW01.html">H Rowan</persName>, <persName xmlns="http://www.tei-c.org/ns/1.0" ref="/people/PLU03.html">major
                  Plunket</persName>, <persName xmlns="http://www.tei-c.org/ns/1.0">M Hawthorn</persName>, <persName xmlns="http://www.tei-c.org/ns/1.0">mrs Beresford
                     &amp; son</persName>, <persName xmlns="http://www.tei-c.org/ns/1.0" ref="/people/ROW01.html">F Rowan</persName> &amp;
                     <persName xmlns="http://www.tei-c.org/ns/1.0" ref="/people/TUR01.html">T T</persName> dine; <seg xmlns="http://www.tei-c.org/ns/1.0" type="dMeeting" subtype="Inv">invités
                        <persName xmlns="http://www.tei-c.org/ns/1.0">Brackenburys</persName> &amp; <persName xmlns="http://www.tei-c.org/ns/1.0" ref="/people/PLU03.html">mrs
                        Plunket</persName></seg>; <seg xmlns="http://www.tei-c.org/ns/1.0" type="dMeeting" subtype="Adv">adv. <persName xmlns="http://www.tei-c.org/ns/1.0">John Nicholson</persName></seg></seg>.</ab>