<?xml version="1.0" encoding="UTF-8"?><ab xmlns="http://www.tei-c.org/ns/1.0" type="dDay" xml:id="g1811-11-01"><date xmlns="http://www.tei-c.org/ns/1.0" when="1811-11-01">Nov. 1. F.</date><ref xmlns="http://www.tei-c.org/ns/1.0" type="dWrote" subtype="letter">Letter to <persName xmlns="http://www.tei-c.org/ns/1.0" ref="/people/FOX02.html">Holland</persName>, 5
               pp</ref>. <ref xmlns="http://www.tei-c.org/ns/1.0" type="dEvent" subtype="PersEvent" target="/events/pe0219.html"><seg xmlns="http://www.tei-c.org/ns/1.0" type="dMeeting" subtype="Cn">Call on <persName xmlns="http://www.tei-c.org/ns/1.0"><placeName xmlns="http://www.tei-c.org/ns/1.0" type="venue">Gatty</placeName></persName>, w. <persName xmlns="http://www.tei-c.org/ns/1.0" ref="/people/CLA02.html">C C</persName> (indenture)</seg></ref>: <seg xmlns="http://www.tei-c.org/ns/1.0" type="dMeeting" subtype="CG"><persName xmlns="http://www.tei-c.org/ns/1.0" type="nah">Graves</persName><hi xmlns="http://www.tei-c.org/ns/1.0" rend="sup">n</hi></seg>, <seg xmlns="http://www.tei-c.org/ns/1.0" type="dMeeting" subtype="CG"><persName xmlns="http://www.tei-c.org/ns/1.0">Elsten</persName></seg> &amp; <seg xmlns="http://www.tei-c.org/ns/1.0" type="dMeeting" subtype="CG"><persName xmlns="http://www.tei-c.org/ns/1.0">M Smith</persName> call</seg>: <seg xmlns="http://www.tei-c.org/ns/1.0" type="dMeal" subtype="TG"><persName xmlns="http://www.tei-c.org/ns/1.0" ref="/people/BUR01.html">Burr</persName> at tea</seg>. <ref xmlns="http://www.tei-c.org/ns/1.0" type="dText" subtype="read" target="/bibl/te1925.html">Cardonne,
                  p. 109</ref>. <seg xmlns="http://www.tei-c.org/ns/1.0" type="dMeeting" subtype="CG"><persName xmlns="http://www.tei-c.org/ns/1.0">Seabrook</persName> calls</seg>.</ab>