<?xml version="1.0" encoding="UTF-8"?><ab xmlns="http://www.tei-c.org/ns/1.0" type="dDay" xml:id="g1814-02-21"><date xmlns="http://www.tei-c.org/ns/1.0" when="1814-02-21">21. M.</date><ref xmlns="http://www.tei-c.org/ns/1.0" type="dWrote" subtype="write" target="/works/unkn01.html">Gen. White, 4 pp</ref>. <seg xmlns="http://www.tei-c.org/ns/1.0" type="dMeeting" subtype="CG"><persName xmlns="http://www.tei-c.org/ns/1.0" ref="/people/MAR01.html">M</persName></seg> &amp; <seg xmlns="http://www.tei-c.org/ns/1.0" type="dMeeting" subtype="CG"><persName xmlns="http://www.tei-c.org/ns/1.0" ref="/people/WHI12.html">Gen. White</persName> call</seg>, <seg xmlns="http://www.tei-c.org/ns/1.0" type="dMeeting" subtype="CG"><persName xmlns="http://www.tei-c.org/ns/1.0">Gill</persName></seg> &amp; <seg xmlns="http://www.tei-c.org/ns/1.0" type="dMeeting" subtype="CG"><persName xmlns="http://www.tei-c.org/ns/1.0"> miss Green, <placeName xmlns="http://www.tei-c.org/ns/1.0" type="venue">Southampton Row</placeName></persName></seg>.</ab>