<?xml version="1.0" encoding="UTF-8"?><ab xmlns="http://www.tei-c.org/ns/1.0" type="dDay" xml:id="g1815-08-04"><date xmlns="http://www.tei-c.org/ns/1.0" when="1815-08-04">4. F.</date><ref xmlns="http://www.tei-c.org/ns/1.0" type="dText" subtype="read" target="/bibl/te2330.html">N Bacon &amp; Brown, p. 58</ref>.
                  <seg xmlns="http://www.tei-c.org/ns/1.0" type="dMeeting" subtype="M">Meet <persName xmlns="http://www.tei-c.org/ns/1.0" ref="/people/HAZ01.html">Hazlit</persName></seg>. <seg xmlns="http://www.tei-c.org/ns/1.0" type="dMeal" subtype="DG"><persName xmlns="http://www.tei-c.org/ns/1.0" ref="/people/MAR01.html">M</persName> dines</seg>: <seg xmlns="http://www.tei-c.org/ns/1.0" type="dMeeting" subtype="CG"><persName xmlns="http://www.tei-c.org/ns/1.0" ref="/people/JON02.html">M Jones</persName> calls</seg>.</ab>