<?xml version="1.0" encoding="UTF-8"?><ab xmlns="http://www.tei-c.org/ns/1.0" type="dDay" xml:id="g1815-09-15"><date xmlns="http://www.tei-c.org/ns/1.0" when="1815-09-15">15. F.</date><seg xmlns="http://www.tei-c.org/ns/1.0" type="dMeeting" subtype="C">Call on <persName xmlns="http://www.tei-c.org/ns/1.0"><placeName xmlns="http://www.tei-c.org/ns/1.0" type="venue">Blacket</placeName></persName></seg>, <seg xmlns="http://www.tei-c.org/ns/1.0" type="dMeeting" subtype="C"><persName xmlns="http://www.tei-c.org/ns/1.0" ref="/people/MIL03.html"><placeName xmlns="http://www.tei-c.org/ns/1.0" type="venue">Miller</placeName></persName></seg>, <seg xmlns="http://www.tei-c.org/ns/1.0" type="dMeeting" subtype="C"><persName xmlns="http://www.tei-c.org/ns/1.0"><placeName xmlns="http://www.tei-c.org/ns/1.0" type="venue">Catlin</placeName></persName></seg> &amp; <seg xmlns="http://www.tei-c.org/ns/1.0" type="dMeeting" subtype="C"><persName xmlns="http://www.tei-c.org/ns/1.0"><placeName xmlns="http://www.tei-c.org/ns/1.0" type="venue">Richards</placeName></persName></seg>: <seg xmlns="http://www.tei-c.org/ns/1.0" type="dMeeting" subtype="Sk">seek <persName xmlns="http://www.tei-c.org/ns/1.0">Thomson</persName></seg>, <seg xmlns="http://www.tei-c.org/ns/1.0" type="dMeeting" subtype="Sk"><persName xmlns="http://www.tei-c.org/ns/1.0">Brookes</persName></seg>, <seg xmlns="http://www.tei-c.org/ns/1.0" type="dMeeting" subtype="Sk"><persName xmlns="http://www.tei-c.org/ns/1.0" ref="/people/DAV01.html">Davison</persName></seg>, <seg xmlns="http://www.tei-c.org/ns/1.0" type="dMeeting" subtype="Sk"><persName xmlns="http://www.tei-c.org/ns/1.0">Silver</persName></seg> &amp; <seg xmlns="http://www.tei-c.org/ns/1.0" type="dMeeting" subtype="Sk"><persName xmlns="http://www.tei-c.org/ns/1.0">Faulder</persName></seg>: <seg xmlns="http://www.tei-c.org/ns/1.0" type="dMeeting" subtype="C">call on <persName xmlns="http://www.tei-c.org/ns/1.0" ref="/people/NOR01.html"><placeName xmlns="http://www.tei-c.org/ns/1.0" type="venue">Northcote</placeName></persName></seg> &amp; <seg xmlns="http://www.tei-c.org/ns/1.0" type="dMeeting" subtype="C"><persName xmlns="http://www.tei-c.org/ns/1.0" ref="/people/LAM01.html"><placeName xmlns="http://www.tei-c.org/ns/1.0" type="venue">Lamb</placeName></persName></seg>: <seg xmlns="http://www.tei-c.org/ns/1.0" type="dMeal" subtype="S">sup at <persName xmlns="http://www.tei-c.org/ns/1.0" ref="/people/HOL05.html"><placeName xmlns="http://www.tei-c.org/ns/1.0" type="venue">L Kenny’s</placeName></persName>, w. <persName xmlns="http://www.tei-c.org/ns/1.0" ref="/people/LAM01.html">Lamb</persName>, <persName xmlns="http://www.tei-c.org/ns/1.0" ref="/people/CLA01.html">M
                  J</persName> &amp; <persName xmlns="http://www.tei-c.org/ns/1.0" ref="/people/IML01.html">F</persName></seg>.</ab>