<?xml version="1.0" encoding="UTF-8"?><ab xmlns="http://www.tei-c.org/ns/1.0" type="dDay" xml:id="g1815-10-13"><date xmlns="http://www.tei-c.org/ns/1.0" when="1815-10-13">13. F.</date><ref xmlns="http://www.tei-c.org/ns/1.0" type="dText" subtype="read">Marriage Alamode, act 1 &amp; 2</ref>. <seg xmlns="http://www.tei-c.org/ns/1.0" type="dMeeting" subtype="CG"><persName xmlns="http://www.tei-c.org/ns/1.0" ref="/people/HAY02.html">Hayward</persName> calls</seg>: <seg xmlns="http://www.tei-c.org/ns/1.0" type="dMeeting" subtype="M">meet
                     <persName xmlns="http://www.tei-c.org/ns/1.0" ref="/people/MAC04.html">Macmillan</persName></seg>.</ab>