<?xml version="1.0" encoding="UTF-8"?><ab xmlns="http://www.tei-c.org/ns/1.0" type="dDay" xml:id="g1817-04-19"><date xmlns="http://www.tei-c.org/ns/1.0" when="1817-04-19">19. Sa.</date><ref xmlns="http://www.tei-c.org/ns/1.0" type="dWrote" subtype="write" target="/works/mand01.html">Mandeville, p. 3</ref>. <seg xmlns="http://www.tei-c.org/ns/1.0" type="dMeeting" subtype="C">Call on <persName xmlns="http://www.tei-c.org/ns/1.0" ref="/people/BOS03.html" type="nah"><placeName xmlns="http://www.tei-c.org/ns/1.0" type="venue">Boswell</placeName></persName><hi xmlns="http://www.tei-c.org/ns/1.0" rend="sup">n</hi></seg>: <seg xmlns="http://www.tei-c.org/ns/1.0" type="dMeeting" subtype="M">meet <persName xmlns="http://www.tei-c.org/ns/1.0">Moore</persName></seg>, <seg xmlns="http://www.tei-c.org/ns/1.0" type="dMeeting" subtype="M"><persName xmlns="http://www.tei-c.org/ns/1.0" ref="/people/PER01.html">Perry</persName></seg>, <seg xmlns="http://www.tei-c.org/ns/1.0" type="dMeeting" subtype="M"><persName xmlns="http://www.tei-c.org/ns/1.0" ref="/people/TAY01.html">J Taylor</persName></seg> &amp; <seg xmlns="http://www.tei-c.org/ns/1.0" type="dMeeting" subtype="M"><persName xmlns="http://www.tei-c.org/ns/1.0" ref="/people/HIL05.html">Hill</persName></seg>: <ref xmlns="http://www.tei-c.org/ns/1.0" type="dEntertainment" subtype="Theat" target="/plays/game01.html"><placeName xmlns="http://www.tei-c.org/ns/1.0"/>theatre, Gamester</ref>.</ab>