<?xml version="1.0" encoding="UTF-8"?><ab xmlns="http://www.tei-c.org/ns/1.0" type="dDay" xml:id="g1817-01-10"><date xmlns="http://www.tei-c.org/ns/1.0" when="1817-01-10">10. F.</date><ref xmlns="http://www.tei-c.org/ns/1.0" type="dWrote" subtype="write" target="/works/mand01.html">Mandeville, p. 12/2</ref>. <seg xmlns="http://www.tei-c.org/ns/1.0" type="dMeal" subtype="D">Dine at <persName xmlns="http://www.tei-c.org/ns/1.0" ref="/people/CUR01.html"><placeName xmlns="http://www.tei-c.org/ns/1.0" type="venue">Curran’s</placeName></persName>, w. <persName xmlns="http://www.tei-c.org/ns/1.0" ref="/people/MEY01.html">Meyler</persName></seg>.</ab>