<?xml version="1.0" encoding="UTF-8"?><ab xmlns="http://www.tei-c.org/ns/1.0" type="dDay" xml:id="g1817-09-28"><date xmlns="http://www.tei-c.org/ns/1.0" when="1817-09-28">Sep. 28. Su.</date><ref xmlns="http://www.tei-c.org/ns/1.0" type="dWrote" subtype="write" target="/works/mand01.html">Mandeville, p. 132/2</ref>. <seg xmlns="http://www.tei-c.org/ns/1.0" type="dMeal" subtype="DG"><persName xmlns="http://www.tei-c.org/ns/1.0" ref="/people/CUR04.html">W Curran</persName> dines</seg>. <seg xmlns="http://www.tei-c.org/ns/1.0" type="dMeeting" subtype="C">Call
                  on <persName xmlns="http://www.tei-c.org/ns/1.0" type="nah"><placeName xmlns="http://www.tei-c.org/ns/1.0" type="venue">G Young</placeName></persName><hi xmlns="http://www.tei-c.org/ns/1.0" rend="sup">n</hi></seg>.</ab>