<?xml version="1.0" encoding="UTF-8"?><ab xmlns="http://www.tei-c.org/ns/1.0" type="dDay" xml:id="g1817-11-17"><date xmlns="http://www.tei-c.org/ns/1.0" when="1817-11-17">17. M.</date><ref xmlns="http://www.tei-c.org/ns/1.0" type="dText" subtype="read" target="/bibl/te2420.html">Atheist’s Tragedy, fin</ref>. <seg xmlns="http://www.tei-c.org/ns/1.0" type="dMeeting" subtype="CG"><persName xmlns="http://www.tei-c.org/ns/1.0" ref="/people/SHE01.html">Shelley</persName> calls</seg>: <seg xmlns="http://www.tei-c.org/ns/1.0" type="dMeal" subtype="D">dine at
                     <persName xmlns="http://www.tei-c.org/ns/1.0" ref="/people/ALD01|ALD05.html"><placeName xmlns="http://www.tei-c.org/ns/1.0" type="venue">Aldis’s</placeName></persName>, w. <persName xmlns="http://www.tei-c.org/ns/1.0">3 Brownings</persName>, <persName xmlns="http://www.tei-c.org/ns/1.0">2 Hickses</persName>,
                     <persName xmlns="http://www.tei-c.org/ns/1.0">Wageman</persName>, <persName xmlns="http://www.tei-c.org/ns/1.0">Powis</persName> &amp;
                     <persName xmlns="http://www.tei-c.org/ns/1.0">Acton</persName>; <seg xmlns="http://www.tei-c.org/ns/1.0" type="dMeeting" subtype="Adv">adv.
                     <persName xmlns="http://www.tei-c.org/ns/1.0">Barber</persName></seg></seg>.</ab>