<?xml version="1.0" encoding="UTF-8"?><ab xmlns="http://www.tei-c.org/ns/1.0" type="dDay" xml:id="g1820-12-27"><date xmlns="http://www.tei-c.org/ns/1.0" when="1820-12-27">27. W.</date><ref xmlns="http://www.tei-c.org/ns/1.0" type="dWrote" subtype="revised" target="/works/popu01.html">Malthus, revise</ref>. <ref xmlns="http://www.tei-c.org/ns/1.0" type="dWrote" subtype="letter">Write to <persName xmlns="http://www.tei-c.org/ns/1.0" ref="/people/ROS01.html">Rosser</persName></ref>. <ref xmlns="http://www.tei-c.org/ns/1.0" type="dText" subtype="read" target="/bibl/te1752.html">Buchanan, 696</ref>: <ref xmlns="http://www.tei-c.org/ns/1.0" type="dText" subtype="read" target="/bibl/te2751.html">Pot of
               Basil</ref>. <seg xmlns="http://www.tei-c.org/ns/1.0" type="dMeal" subtype="DG"><persName xmlns="http://www.tei-c.org/ns/1.0" ref="/people/FAI01.html">Fairley</persName> 1/2 dines</seg>.</ab>