<?xml version="1.0" encoding="UTF-8"?><ab xmlns="http://www.tei-c.org/ns/1.0" type="dDay" xml:id="g1820-08-27"><date xmlns="http://www.tei-c.org/ns/1.0" when="1820-08-27">Aug. 27. Su.</date><ref xmlns="http://www.tei-c.org/ns/1.0" type="dWrote" subtype="revised" target="/works/popu01.html">Malthus, revise</ref>. <ref xmlns="http://www.tei-c.org/ns/1.0" type="dText" subtype="read" target="/bibl/te1073.html">Scornful Lady, acts 1 &amp; 2</ref>. <seg xmlns="http://www.tei-c.org/ns/1.0" type="dMeeting" subtype="M">Meet <persName xmlns="http://www.tei-c.org/ns/1.0" ref="/people/PER01.html">Perry</persName></seg> &amp; <seg xmlns="http://www.tei-c.org/ns/1.0" type="dMeeting" subtype="M"><persName xmlns="http://www.tei-c.org/ns/1.0">Tegart</persName></seg>.</ab>