<?xml version="1.0" encoding="UTF-8"?><ab xmlns="http://www.tei-c.org/ns/1.0" type="dDay" xml:id="g1821-09-19"><date xmlns="http://www.tei-c.org/ns/1.0" when="1821-09-19">19. W.</date><ref xmlns="http://www.tei-c.org/ns/1.0" type="dText" subtype="read" target="/bibl/te2764.html">Marino, st. 81</ref>. <seg xmlns="http://www.tei-c.org/ns/1.0" type="dMeeting" subtype="Sk">Seek <persName xmlns="http://www.tei-c.org/ns/1.0" ref="/people/HON01.html">Hone</persName></seg>: <seg xmlns="http://www.tei-c.org/ns/1.0" type="dMeeting" subtype="C">call on <persName xmlns="http://www.tei-c.org/ns/1.0" ref="/people/DAV01.html"><placeName xmlns="http://www.tei-c.org/ns/1.0" type="venue">Davison</placeName></persName></seg> &amp; <seg xmlns="http://www.tei-c.org/ns/1.0" type="dMeeting" subtype="C"><persName xmlns="http://www.tei-c.org/ns/1.0" ref="/people/MAC04.html"><placeName xmlns="http://www.tei-c.org/ns/1.0" type="venue">Macmillan</placeName></persName></seg>: <seg xmlns="http://www.tei-c.org/ns/1.0" type="dMeal" subtype="TG"><persName xmlns="http://www.tei-c.org/ns/1.0" ref="/people/BOO01.html">Booth</persName> at tea</seg>: <seg xmlns="http://www.tei-c.org/ns/1.0" type="dMeal" subtype="SG"><persName xmlns="http://www.tei-c.org/ns/1.0" ref="/people/BOO01.html">Booth</persName> &amp; <persName xmlns="http://www.tei-c.org/ns/1.0" ref="/people/HUD01.html">Hudson</persName> sup</seg>.</ab>