<?xml version="1.0" encoding="UTF-8"?><ab xmlns="http://www.tei-c.org/ns/1.0" type="dDay" xml:id="g1828-01-17"><date xmlns="http://www.tei-c.org/ns/1.0" when="1828-01-17">17. Th.</date><ref xmlns="http://www.tei-c.org/ns/1.0" type="dWrote" subtype="write" target="/works/comm01.html">Commonwealth, p. 197/2</ref>. <ref xmlns="http://www.tei-c.org/ns/1.0" type="dText" subtype="read" target="/bibl/te0063.html">Livy, c. 38</ref>. <seg xmlns="http://www.tei-c.org/ns/1.0" type="dMeal" subtype="S">Sup at <persName xmlns="http://www.tei-c.org/ns/1.0" ref="/people/HOD01.html"><placeName xmlns="http://www.tei-c.org/ns/1.0" type="venue">Hodget’s</placeName></persName>, w. <persName xmlns="http://www.tei-c.org/ns/1.0" ref="/people/BOW01.html">Bowring</persName> &amp; <persName xmlns="http://www.tei-c.org/ns/1.0">miss
                     Twamley</persName></seg>. <ref xmlns="http://www.tei-c.org/ns/1.0" type="dEvent" subtype="Temp">48 ½ / 55</ref></ab>