<?xml version="1.0" encoding="UTF-8"?><ab xmlns="http://www.tei-c.org/ns/1.0" type="dDay" xml:id="g1828-04-17"><date xmlns="http://www.tei-c.org/ns/1.0" when="1828-04-17">17. Th.</date><ref xmlns="http://www.tei-c.org/ns/1.0" type="dWrote" subtype="write" target="/works/comm01.html">Commonwealth, 1 1/2 pp</ref>. <ref xmlns="http://www.tei-c.org/ns/1.0" type="dText" subtype="read" target="/bibl/te0063.html">Livy, c. 33</ref>. <seg xmlns="http://www.tei-c.org/ns/1.0" type="dMeeting" subtype="CG"><persName xmlns="http://www.tei-c.org/ns/1.0" ref="/people/REY05.html">F Reynolds</persName> calls</seg>: <ref xmlns="http://www.tei-c.org/ns/1.0" type="dEntertainment" subtype="Theat" target="/plays/love02.html"><placeName xmlns="http://www.tei-c.org/ns/1.0" type="DL"/>theatre, Love for Love; <seg xmlns="http://www.tei-c.org/ns/1.0" type="dMeeting" subtype="Adv">adv. <persName xmlns="http://www.tei-c.org/ns/1.0" ref="/people/SKE01.html">Skeffington</persName> &amp; <persName xmlns="http://www.tei-c.org/ns/1.0" ref="/people/MIL03.html">Miller</persName></seg></ref>. <ref xmlns="http://www.tei-c.org/ns/1.0" type="dEvent" subtype="Temp">59 / 62 ½</ref></ab>