<?xml version="1.0" encoding="UTF-8"?><ab xmlns="http://www.tei-c.org/ns/1.0" type="dDay" xml:id="g1830-10-28"><date xmlns="http://www.tei-c.org/ns/1.0" when="1830-10-28">28. Th.</date><ref xmlns="http://www.tei-c.org/ns/1.0" type="dWrote" subtype="write" target="/works/thou01.html">Fame, p. 12</ref>.<ref xmlns="http://www.tei-c.org/ns/1.0" type="dText" subtype="read" target="/bibl/te3272.html"> Homer,
                  X, v. 76</ref>: <ref xmlns="http://www.tei-c.org/ns/1.0" type="dText" subtype="read" target="/bibl/te0717.html">Crusoe, p. 130</ref>. <emph xmlns="http://www.tei-c.org/ns/1.0" rend="red"><ref xmlns="http://www.tei-c.org/ns/1.0" type="dEvent" subtype="Publ" target="/events/pu0256.html"><placeName xmlns="http://www.tei-c.org/ns/1.0">Antwerp</placeName> burned</ref>.</emph><ref xmlns="http://www.tei-c.org/ns/1.0" type="dEvent" subtype="Temp">58 /
                  64</ref></ab>