<?xml version="1.0" encoding="UTF-8"?><ab xmlns="http://www.tei-c.org/ns/1.0" type="dDay" xml:id="g1830-01-04"><date xmlns="http://www.tei-c.org/ns/1.0" when="1830-01-04">4. <emph xmlns="http://www.tei-c.org/ns/1.0" rend="deleted">Tu.</emph> M.</date><ref xmlns="http://www.tei-c.org/ns/1.0" type="dWrote" subtype="revised" target="/works/clou01.html">Cloudesley, revise</ref>. <ref xmlns="http://www.tei-c.org/ns/1.0" type="dText" subtype="read" target="/bibl/te3272.html">Homer, Lib. X, v. 42</ref>:<ref xmlns="http://www.tei-c.org/ns/1.0" type="dText" subtype="read" target="/bibl/te3288.html"> 3<hi xmlns="http://www.tei-c.org/ns/1.0" rend="sup">d</hi> Munster, p. 302, fin</ref>.<seg xmlns="http://www.tei-c.org/ns/1.0" type="dMeeting" subtype="C"> Call on <persName xmlns="http://www.tei-c.org/ns/1.0" ref="/people/GOD07.html" type="nah"><placeName xmlns="http://www.tei-c.org/ns/1.0" type="venue">W</placeName></persName><hi xmlns="http://www.tei-c.org/ns/1.0" rend="sup">n</hi></seg>.<ref xmlns="http://www.tei-c.org/ns/1.0" type="dEvent" subtype="Temp"> 45 / 49</ref></ab>