<?xml version="1.0" encoding="UTF-8"?><ab xmlns="http://www.tei-c.org/ns/1.0" type="dDay" xml:id="g1831-01-01"><date xmlns="http://www.tei-c.org/ns/1.0" when="1831-01-01">1831. Jan. 1. Sa.</date><ref xmlns="http://www.tei-c.org/ns/1.0" type="dWrote" subtype="write" target="/works/thou01.html">Self-Complacency, p. 10</ref>: <ref xmlns="http://www.tei-c.org/ns/1.0" type="dWrote" subtype="write" target="/works/thou01.html">Phrenology, p. 4</ref>. <ref xmlns="http://www.tei-c.org/ns/1.0" type="dText" subtype="read" target="/bibl/te3355.html">Homer,
                  v. 421</ref>. <seg xmlns="http://www.tei-c.org/ns/1.0" type="dMeeting" subtype="CG"><persName xmlns="http://www.tei-c.org/ns/1.0" ref="/people/UWI01.html">Uwins</persName> calls</seg>: <seg xmlns="http://www.tei-c.org/ns/1.0" type="dMeeting" subtype="C">call
                  on <persName xmlns="http://www.tei-c.org/ns/1.0" ref="/people/HOD01.html"><placeName xmlns="http://www.tei-c.org/ns/1.0" type="venue">S Hodgets</placeName></persName></seg>. <ref xmlns="http://www.tei-c.org/ns/1.0" type="dEvent" subtype="Temp">47 ½ / 51</ref></ab>