<?xml version="1.0" encoding="UTF-8"?><ab xmlns="http://www.tei-c.org/ns/1.0" type="dDay" xml:id="g1833-11-23"><date xmlns="http://www.tei-c.org/ns/1.0" when="1833-11-23">23. Sa.</date><ref xmlns="http://www.tei-c.org/ns/1.0" type="dWrote" subtype="write" target="/works/necr01.html">Necromancers, 1 page</ref>. <ref xmlns="http://www.tei-c.org/ns/1.0" type="dEntertainment" subtype="Museo" target="/events/mu0012.html"><placeName xmlns="http://www.tei-c.org/ns/1.0">Library, D <emph xmlns="http://www.tei-c.org/ns/1.0" rend="deleted">L</emph> C</placeName>; <ref xmlns="http://www.tei-c.org/ns/1.0" type="dText" subtype="read" target="/bibl/te3572.html">Biographie</ref></ref>. <ref xmlns="http://www.tei-c.org/ns/1.0" type="dText" subtype="read" target="/bibl/te3571.html">Trevelyan, p. 292; Vol. III, p. 85</ref>.
                  <ref xmlns="http://www.tei-c.org/ns/1.0" type="dEntertainment" subtype="Theat">Theatre, <placeName xmlns="http://www.tei-c.org/ns/1.0">C G</placeName>,
               repelled</ref>. <ref xmlns="http://www.tei-c.org/ns/1.0" type="dEvent" subtype="Temp">59 ½ / 66</ref><add xmlns="http://www.tei-c.org/ns/1.0"><ref xmlns="http://www.tei-c.org/ns/1.0" type="dEvent" subtype="PersHlth" target="/events/he0000|he0072.html"><foreign xmlns="http://www.tei-c.org/ns/1.0">Bien</foreign>, 10 days</ref>.</add></ab>