<?xml version="1.0" encoding="UTF-8"?><ab xmlns="http://www.tei-c.org/ns/1.0" type="dDay" xml:id="g1833-09-26"><date xmlns="http://www.tei-c.org/ns/1.0" when="1833-09-26">26. Th.</date><ref xmlns="http://www.tei-c.org/ns/1.0" type="dText" subtype="read" target="/bibl/te3560.html">Selene, p. 241</ref>. <seg xmlns="http://www.tei-c.org/ns/1.0" type="dMeeting" subtype="CGn"><persName xmlns="http://www.tei-c.org/ns/1.0" ref="/people/RIC01.html">Rickman &amp; <foreign xmlns="http://www.tei-c.org/ns/1.0">femme</foreign></persName></seg>, &amp; <seg xmlns="http://www.tei-c.org/ns/1.0" type="dMeeting" subtype="CG"><persName xmlns="http://www.tei-c.org/ns/1.0" ref="/people/COO06.html">Fennimore Cooper</persName> call</seg>: <seg xmlns="http://www.tei-c.org/ns/1.0" type="dMeal" subtype="D">dine at <persName xmlns="http://www.tei-c.org/ns/1.0" ref="/people/POO02.html"><placeName xmlns="http://www.tei-c.org/ns/1.0" type="venue">Poole’s</placeName></persName>, w. <persName xmlns="http://www.tei-c.org/ns/1.0" ref="/people/CAM01.html">T Campbel</persName>, <persName xmlns="http://www.tei-c.org/ns/1.0" ref="/people/PIC01.html">Pickersgil</persName>, <persName xmlns="http://www.tei-c.org/ns/1.0">Denman</persName> &amp;
                  <persName xmlns="http://www.tei-c.org/ns/1.0">Norton</persName></seg>. <ref xmlns="http://www.tei-c.org/ns/1.0" type="dEvent" subtype="Temp">64 / 73</ref></ab>