<?xml version="1.0" encoding="UTF-8"?><ab xmlns="http://www.tei-c.org/ns/1.0" type="dDay" xml:id="g1834-06-17"><date xmlns="http://www.tei-c.org/ns/1.0" when="1834-06-17">17. Tu.</date><ref xmlns="http://www.tei-c.org/ns/1.0" type="dWrote" subtype="write" target="/works/self02.html">Self-Love, 9 lines</ref>.<ref xmlns="http://www.tei-c.org/ns/1.0" type="dText" subtype="read" target="/bibl/te3607.html">
                  Necromancers, p. 437</ref>. <seg xmlns="http://www.tei-c.org/ns/1.0" type="dMeeting" subtype="C">Call on <persName xmlns="http://www.tei-c.org/ns/1.0"><placeName xmlns="http://www.tei-c.org/ns/1.0" type="venue">Mason</placeName></persName></seg>: <seg xmlns="http://www.tei-c.org/ns/1.0" type="dMeeting" subtype="CG"><persName xmlns="http://www.tei-c.org/ns/1.0" ref="/people/GAS02.html">mrs Gaskel</persName></seg>, <seg xmlns="http://www.tei-c.org/ns/1.0" type="dMeeting" subtype="CG"><persName xmlns="http://www.tei-c.org/ns/1.0" ref="/people/JOH01.html">Johnson</persName></seg> &amp; <seg xmlns="http://www.tei-c.org/ns/1.0" type="dMeeting" subtype="CG"><persName xmlns="http://www.tei-c.org/ns/1.0">Bakewel</persName> call</seg>.<ref xmlns="http://www.tei-c.org/ns/1.0" type="dEvent" subtype="Temp"> 68 ½ /
               71</ref></ab>